r2_transformations-0.1.0.dist-info/licenses/LICENSE
transformations/__init__.py
transformations/_transformations.py
transformations/_transformations_quat.py
transformations/_types.py
transformations/transformations.py
transformations/transformations_test.py
transformations/jax_transformations/__init__.py
transformations/jax_transformations/transformations.py
transformations/jax_transformations/transformations_test.py
r2_transformations-0.1.0.dist-info/METADATA
r2_transformations-0.1.0.dist-info/WHEEL
r2_transformations-0.1.0.dist-info/top_level.txt
r2_transformations-0.1.0.dist-info/RECORD
