Metadata-Version: 2.4
Name: r2-transformations
Version: 0.1.0
Summary: Library for rigid-body transformations, including velocities and forces.
Author-email: Reimagine Robotics <info@reimaginerobotics.ai>
License-Expression: Apache-2.0
Project-URL: Repository, https://github.com/Reimagine-Robotics/transformations
Requires-Python: >=3.10
License-File: LICENSE
Requires-Dist: pip>=20.0.2
Requires-Dist: absl-py>=0.9.0
Requires-Dist: numpy>=1.16.0
Provides-Extra: jax
Requires-Dist: jax>=0.4.13; extra == "jax"
Provides-Extra: quaternion
Requires-Dist: numpy-quaternion; extra == "quaternion"
Provides-Extra: dev
Requires-Dist: pyink; extra == "dev"
Requires-Dist: jax>=0.4.13; extra == "dev"
Requires-Dist: numpy-quaternion; extra == "dev"
Dynamic: license-file
